supabase_functions/__init__.py
supabase_functions/_async/__init__.py
supabase_functions/_async/functions_client.py
supabase_functions/_sync/__init__.py
supabase_functions/_sync/functions_client.py
supabase_functions/errors.py
supabase_functions/py.typed
supabase_functions/utils.py
supabase_functions/version.py
supabase_functions-2.23.1.dist-info/WHEEL
supabase_functions-2.23.1.dist-info/METADATA
supabase_functions-2.23.1.dist-info/RECORD
