Metadata-Version: 2.4
Name: supabase-functions
Version: 2.23.1
Summary: Library for Supabase Functions
Author: Joel Lee, Andrew Smith
Author-email: Joel Lee <joel@joellee.org>, Andrew Smith <a.smith@silentworks.co.uk>
License-Expression: MIT
Requires-Dist: httpx[http2]>=0.26,<0.29
Requires-Dist: strenum>=0.4.15
Requires-Dist: yarl>=1.20.1
Maintainer: Leonardo Santiago
Maintainer-email: Leonardo Santiago <leonardo.santiago@supabase.io>
Requires-Python: >=3.9
Project-URL: changelog, https://github.com/supabase/supabase-py/tree/main/CHANGELOG.md
Project-URL: homepage, https://github.com/supabase/supabase-py/tree/main/src/functions
Project-URL: repository, https://github.com/supabase/supabase-py
